{
  "id": "campaign_guides/legacy_of_the_ancestors/79_ranger_cache_loa",
  "title": "79. Ranger Cache (LOA)",
  "content": "<blockquote id=\"narration_1\"><p>You barely notice the sigil carved into a nearby boulder. You don\u2019t see any sign of the Ranger cache, but you whistle the five tones known to all Rangers of the Valley. The illusion of the lichen-covered boulder flares and fades as the lenser deactivates, revealing four carbonforged chests bolted to the ground.</p></blockquote>",
  "anchors": [],
  "links": [],
  "lookup": [],
  "url": "/docs/campaign_guides/legacy_of_the_ancestors/ranger_cache"
}