{
  "id": "campaign_guides/lure_of_the_valley/91_biscuit_delivery/91_4",
  "title": "91.4",
  "content": "<blockquote><p>You feel a tug on your backpack and turn to see a young girl suddenly walking beside you.</p><p>\u201cHi!\u201d she says. \u201cDo you smell something? Is Hy Pimpot baking his famous juniper biscuits? Can I have one? Which way to the kitchen?\u201d</p></blockquote><p color=\"blue\"><i>Clear Quisi with <icon icon=\"progress\">&nbsp;</icon> to help her find the kitchen.</i></p>",
  "links": [],
  "lookup": null,
  "url": "/docs/campaign_guides/lure_of_the_valley/biscuit_delivery/91_4"
}