{
  "id": "campaign_guides/legacy_of_the_ancestors/123_lost_lutrinal/123_3",
  "lookup_group": "campaign_guides/legacy_of_the_ancestors",
  "lookup_id": "123.3",
  "title": "123.3",
  "content": [
    {
      "type": "blockquote",
      "items": [
        {
          "type": "p",
          "items": [
            {
              "type": "text",
              "text": "You have to admit, as you watch the lutrinal dive into the water with an almighty splash and playfully chase after a couple of its kind, that this brief sojourn to the surface has been good for your spirits. You smile to yourself and prepare to head out."
            }
          ]
        }
      ]
    },
    {
      "type": "p",
      "items": [
        {
          "type": "text",
          "text": "Search the Lakeshore set for the Lutrinal Holt and put it into play."
        }
      ]
    },
    {
      "type": "blockquote",
      "items": [
        {
          "type": "p",
          "items": [
            {
              "type": "text",
              "text": "A trilling noise stops you, and you turn to see the lutrinal looking inquisitively in your direction. You take a few steps away, but after a moment, it bounds a couple steps closer. You shoo the little scamp back toward the water, but it seems it will not be deterred. Suddenly, it leaps upon you, and both you and the lutrinal tumble to the ground. It sits victoriously on your chest and licks your face with its rough tongue. Clearly, you\u2019ve made a friend for life. You decide that \"Stripe\" would be a perfect name."
            }
          ]
        }
      ]
    },
    {
      "type": "p",
      "items": [
        {
          "type": "text",
          "text": "Gain the Stripe, Loyal Lutrinal reward card. Return"
        },
        {
          "type": "strong",
          "items": [
            {
              "type": "text",
              "text": "HELPING HAND"
            }
          ]
        },
        {
          "type": "text",
          "text": "to the collection. Record"
        },
        {
          "type": "span",
          "items": [
            {
              "type": "text",
              "text": "RETURNED TO THE HOLT"
            }
          ],
          "color": "blue"
        },
        {
          "type": "text",
          "text": "on the campaign tracker. Return Lost Lutrinal to the collection and permanently remove it from the Chimney set."
        }
      ]
    }
  ],
  "items": [],
  "url": "/docs/campaign_guides/legacy_of_the_ancestors/lost_lutrinal/123_3"
}