{
  "id": "updates/card_errata/mission_set_card_18_of_34",
  "title": "Mission Set Card 18 of 34",
  "content": "<p><i>This change affects the first printing. Revised text is <code>highlighted</code>.</i></p><p>Replace the \u201cwhen\u201d condition with the following:</p><blockquote><p>When a Reclaimer Grub is cleared <code>while at the Alluvial Ruins</code>, place 1 progress on this mission.</p></blockquote><p><img src=\"https://thelivingvalley.earthbornegames.com/assets/images/EBR_Cards_Missions_18of34-7d54cfda62557332318e762523ea014c.png#errata_cards\" /></p>",
  "links": [],
  "lookup": null,
  "url": "/docs/updates/card_errata/mission_18_of_34"
}